PyParanoid-0.4.1.data/scripts/BuildGroups.py
PyParanoid-0.4.1.data/scripts/IdentifyOrthologs.py
PyParanoid-0.4.1.data/scripts/PropagateGroups.py
PyParanoid-0.4.1.data/scripts/inparanoid2.pl
pyparanoid/__init__.py
pyparanoid/genomedb.py
pyparanoid/genomeplot.py
pyparanoid/pyparanoid.py
PyParanoid-0.4.1.dist-info/LICENSE.txt
PyParanoid-0.4.1.dist-info/METADATA
PyParanoid-0.4.1.dist-info/WHEEL
PyParanoid-0.4.1.dist-info/top_level.txt
PyParanoid-0.4.1.dist-info/RECORD
