Metadata-Version: 2.1
Name: PyParanoid
Version: 0.4.1
Summary: Fast and scalable homolog detection for thousands of genomes
Home-page: https://github.com/ryanmelnyk/PyParanoid
Author: Ryan A. Melnyk
Author-email: schmelnyk@gmail.com
License: MIT
Platform: UNKNOWN
Classifier: Programming Language :: Python
Classifier: Programming Language :: Python :: 3
Requires-Dist: biopython
Requires-Dist: numpy
Requires-Dist: ncbi-genome-download
Requires-Dist: pandas
Requires-Dist: seaborn
Requires-Dist: matplotlib
Requires-Dist: reportlab
Requires-Dist: ijson
Requires-Dist: ete3
